llm_sepweight/__init__.py
llm_sepweight/dumping.py
llm_sepweight/filenames.py
llm_sepweight/llama_loading.py
llm_sepweight/loading.py
llm_sepweight/part_module.py
llm_sepweight/part_state_dict.py
llm_sepweight/pth_conversion.py
llm_sepweight/safetensors_conversion.py
llm_sepweight/utils.py
llm_sepweight-0.10.0.dist-info/METADATA
llm_sepweight-0.10.0.dist-info/WHEEL
llm_sepweight-0.10.0.dist-info/top_level.txt
llm_sepweight-0.10.0.dist-info/RECORD
