Metadata-Version: 2.1
Name: llm-sepweight
Version: 0.10.0
Summary: Microlib for converting LLM weights into sepweight format
Author-email: Hristo Vrigazov <hvrigazov@gmail.com>
Project-URL: Homepage, https://github.com/microlib-org/llm_microlibs/llm_sepweight
Classifier: License :: OSI Approved :: MIT License
Classifier: Programming Language :: Python
Classifier: Programming Language :: Python :: 3
Requires-Python: >=3.8
Requires-Dist: torch
Provides-Extra: dev
Requires-Dist: safetensors ; extra == 'dev'
Requires-Dist: pytest ; extra == 'dev'
Requires-Dist: tqdm ; extra == 'dev'
Requires-Dist: pytest-dotenv ; extra == 'dev'
